pretzels/functions.py
pretzels/tests.py
pretzels-1.0.4.dist-info/LICENSE
pretzels-1.0.4.dist-info/METADATA
pretzels-1.0.4.dist-info/WHEEL
pretzels-1.0.4.dist-info/entry_points.txt
pretzels-1.0.4.dist-info/top_level.txt
pretzels-1.0.4.dist-info/RECORD
