Metadata-Version: 2.1
Name: pretzels
Version: 1.0.4
Summary: AA Azure Workflow Helper Functions
Home-page: https://github.com/serinamarie/pretzels
Author: Serina Grill
Author-email: serina.grill@aa.com
License: MIT
Platform: UNKNOWN
Classifier: License :: OSI Approved :: MIT License
Classifier: Programming Language :: Python :: 3
Classifier: Programming Language :: Python :: 3.7
